wppm/__init__.py
wppm/associate.py
wppm/diff.py
wppm/hash.py
wppm/packagemetadata.py
wppm/piptree.py
wppm/utils.py
wppm/wheelhouse.py
wppm/wppm.py
wppm-17.0.20250628.dist-info/entry_points.txt
wppm-17.0.20250628.dist-info/LICENSE
wppm-17.0.20250628.dist-info/WHEEL
wppm-17.0.20250628.dist-info/METADATA
wppm-17.0.20250628.dist-info/RECORD
