Metadata-Version: 2.1
Name: wppm
Version: 17.0.20250628
Summary: WinPython Package Management
Keywords: Portable,Windows
Author: Pierre Raybaut, stonebig
Requires-Python: >=3.10
Classifier: License :: OSI Approved :: MIT License
Classifier: Operating System :: MacOS
Classifier: Operating System :: Microsoft :: Windows
Classifier: Operating System :: OS Independent
Classifier: Operating System :: POSIX
Classifier: Operating System :: Unix
Classifier: Programming Language :: Python :: 3
Classifier: Development Status :: 5 - Production/Stable
Classifier: Topic :: Scientific/Engineering
Classifier: Topic :: Software Development :: Widget Sets
Project-URL: Documentation, https://winpython.github.io/
Project-URL: Source, https://github.com/winpython/winpython
